{
"meta":{"test_sets":[],"test_metrics":[],"learn_metrics":[{"best_value":"Min","name":"RMSE"}],"launch_mode":"Train","parameters":"","iteration_count":100,"learn_sets":["learn"],"name":"experiment"},
"iterations":[
{"learn":[14.005006],"iteration":0,"passed_time":0.001050651548,"remaining_time":0.1040145032},
{"learn":[13.14441192],"iteration":1,"passed_time":0.001901017308,"remaining_time":0.0931498481},
{"learn":[12.34258257],"iteration":2,"passed_time":0.002713755505,"remaining_time":0.08774476131},
{"learn":[11.64527793],"iteration":3,"passed_time":0.003452704783,"remaining_time":0.08286491479},
{"learn":[11.02766183],"iteration":4,"passed_time":0.004557451556,"remaining_time":0.08659157956},
{"learn":[10.43485794],"iteration":5,"passed_time":0.005515100746,"remaining_time":0.08640324502},
{"learn":[9.890641275],"iteration":6,"passed_time":0.006495568961,"remaining_time":0.08629827334},
{"learn":[9.492161212],"iteration":7,"passed_time":0.007471069399,"remaining_time":0.08591729808},
{"learn":[9.105082953],"iteration":8,"passed_time":0.008487367734,"remaining_time":0.0858167182},
{"learn":[8.674157135],"iteration":9,"passed_time":0.009473892596,"remaining_time":0.08526503337},
{"learn":[8.341743544],"iteration":10,"passed_time":0.01045336563,"remaining_time":0.08457723103},
{"learn":[8.049372916],"iteration":11,"passed_time":0.01139796279,"remaining_time":0.08358506043},
{"learn":[7.757318612],"iteration":12,"passed_time":0.01241168391,"remaining_time":0.08306280771},
{"learn":[7.522206899],"iteration":13,"passed_time":0.01346370466,"remaining_time":0.08270561433},
{"learn":[7.297756655],"iteration":14,"passed_time":0.0143498596,"remaining_time":0.08131587104},
{"learn":[7.088359431],"iteration":15,"passed_time":0.01526579796,"remaining_time":0.08014543931},
{"learn":[6.882113791],"iteration":16,"passed_time":0.01622650167,"remaining_time":0.07922350814},
{"learn":[6.704728832],"iteration":17,"passed_time":0.01709462277,"remaining_time":0.07787550374},
{"learn":[6.563881962],"iteration":18,"passed_time":0.01795183048,"remaining_time":0.07653148783},
{"learn":[6.418790279],"iteration":19,"passed_time":0.01886005013,"remaining_time":0.0754402005},
{"learn":[6.315756953],"iteration":20,"passed_time":0.01978622172,"remaining_time":0.07443388171},
{"learn":[6.210157751],"iteration":21,"passed_time":0.02089498167,"remaining_time":0.07408220773},
{"learn":[6.115058449],"iteration":22,"passed_time":0.0217444902,"remaining_time":0.07279677154},
{"learn":[6.014819884],"iteration":23,"passed_time":0.02270614998,"remaining_time":0.07190280828},
{"learn":[5.93117229],"iteration":24,"passed_time":0.02361299527,"remaining_time":0.0708389858},
{"learn":[5.844857622],"iteration":25,"passed_time":0.02464496674,"remaining_time":0.07014336688},
{"learn":[5.771145213],"iteration":26,"passed_time":0.02574926277,"remaining_time":0.06961837712},
{"learn":[5.704018229],"iteration":27,"passed_time":0.0267691844,"remaining_time":0.0688350456},
{"learn":[5.665806474],"iteration":28,"passed_time":0.0278001666,"remaining_time":0.06806247684},
{"learn":[5.616500369],"iteration":29,"passed_time":0.02883633383,"remaining_time":0.06728477894},
{"learn":[5.558023666],"iteration":30,"passed_time":0.02979038518,"remaining_time":0.06630763154},
{"learn":[5.510080976],"iteration":31,"passed_time":0.03060880711,"remaining_time":0.06504371511},
{"learn":[5.468747792],"iteration":32,"passed_time":0.03154109695,"remaining_time":0.06403798472},
{"learn":[5.429275534],"iteration":33,"passed_time":0.03244648967,"remaining_time":0.0629843623},
{"learn":[5.402117324],"iteration":34,"passed_time":0.03336216357,"remaining_time":0.06195830377},
{"learn":[5.367635151],"iteration":35,"passed_time":0.03426381755,"remaining_time":0.06091345342},
{"learn":[5.345181232],"iteration":36,"passed_time":0.03515523904,"remaining_time":0.05985892052},
{"learn":[5.319151269],"iteration":37,"passed_time":0.03607080043,"remaining_time":0.0588523586},
{"learn":[5.296134146],"iteration":38,"passed_time":0.03697060569,"remaining_time":0.05782581916},
{"learn":[5.269629003],"iteration":39,"passed_time":0.03800663387,"remaining_time":0.05700995081},
{"learn":[5.251147059],"iteration":40,"passed_time":0.0390372734,"remaining_time":0.05617558855},
{"learn":[5.248003302],"iteration":41,"passed_time":0.03937780413,"remaining_time":0.05437887237},
{"learn":[5.232376509],"iteration":42,"passed_time":0.04018761654,"remaining_time":0.05327195681},
{"learn":[5.213524255],"iteration":43,"passed_time":0.04108311502,"remaining_time":0.05228760094},
{"learn":[5.189691584],"iteration":44,"passed_time":0.04211037655,"remaining_time":0.05146823801},
{"learn":[5.166052198],"iteration":45,"passed_time":0.04307112525,"remaining_time":0.05056175573},
{"learn":[5.140406659],"iteration":46,"passed_time":0.04401783891,"remaining_time":0.0496371375},
{"learn":[5.118929684],"iteration":47,"passed_time":0.04491067756,"remaining_time":0.04865323402},
{"learn":[5.108792602],"iteration":48,"passed_time":0.04578886959,"remaining_time":0.04765780304},
{"learn":[5.098141225],"iteration":49,"passed_time":0.04680843527,"remaining_time":0.04680843527},
{"learn":[5.085926393],"iteration":50,"passed_time":0.0476676455,"remaining_time":0.04579832607},
{"learn":[5.067816804],"iteration":51,"passed_time":0.04865729791,"remaining_time":0.04491442884},
{"learn":[5.049834901],"iteration":52,"passed_time":0.04964825608,"remaining_time":0.04402769878},
{"learn":[5.03838627],"iteration":53,"passed_time":0.05051296893,"remaining_time":0.04302956613},
{"learn":[5.033534248],"iteration":54,"passed_time":0.05106430491,"remaining_time":0.04177988583},
{"learn":[5.023726885],"iteration":55,"passed_time":0.0519526634,"remaining_time":0.04081994982},
{"learn":[5.01290392],"iteration":56,"passed_time":0.05289114415,"remaining_time":0.03990033682},
{"learn":[5.005569127],"iteration":57,"passed_time":0.05398437444,"remaining_time":0.03909213322},
{"learn":[4.989969032],"iteration":58,"passed_time":0.05485719664,"remaining_time":0.03812110275},
{"learn":[4.976762446],"iteration":59,"passed_time":0.05580767929,"remaining_time":0.03720511953},
{"learn":[4.967222715],"iteration":60,"passed_time":0.05677153009,"remaining_time":0.03629655202},
{"learn":[4.954407599],"iteration":61,"passed_time":0.05779510857,"remaining_time":0.03542280848},
{"learn":[4.942125056],"iteration":62,"passed_time":0.05861701879,"remaining_time":0.03442586818},
{"learn":[4.930230716],"iteration":63,"passed_time":0.05952568623,"remaining_time":0.03348319851},
{"learn":[4.921695642],"iteration":64,"passed_time":0.06050803009,"remaining_time":0.03258124697},
{"learn":[4.906405625],"iteration":65,"passed_time":0.06143298003,"remaining_time":0.03164729274},
{"learn":[4.894330248],"iteration":66,"passed_time":0.06235528562,"remaining_time":0.03071230486},
{"learn":[4.88211557],"iteration":67,"passed_time":0.06339723065,"remaining_time":0.02983399089},
{"learn":[4.877946398],"iteration":68,"passed_time":0.06435276849,"remaining_time":0.02891211338},
{"learn":[4.863182126],"iteration":69,"passed_time":0.06529829849,"remaining_time":0.02798498507},
{"learn":[4.84646533],"iteration":70,"passed_time":0.06616208404,"remaining_time":0.02702394982},
{"learn":[4.838014752],"iteration":71,"passed_time":0.06710085397,"remaining_time":0.02609477654},
{"learn":[4.82981137],"iteration":72,"passed_time":0.06817405786,"remaining_time":0.0252150625},
{"learn":[4.817094767],"iteration":73,"passed_time":0.06935203879,"remaining_time":0.02436693255},
{"learn":[4.808314151],"iteration":74,"passed_time":0.07050108724,"remaining_time":0.02350036241},
{"learn":[4.796235023],"iteration":75,"passed_time":0.07143108168,"remaining_time":0.02255718369},
{"learn":[4.784434534],"iteration":76,"passed_time":0.07235435221,"remaining_time":0.02161233897},
{"learn":[4.774402487],"iteration":77,"passed_time":0.07325832003,"remaining_time":0.02066260308},
{"learn":[4.76731896],"iteration":78,"passed_time":0.07421721743,"remaining_time":0.01972862742},
{"learn":[4.75934113],"iteration":79,"passed_time":0.07521022424,"remaining_time":0.01880255606},
{"learn":[4.754106378],"iteration":80,"passed_time":0.07611034745,"remaining_time":0.01785304446},
{"learn":[4.744002932],"iteration":81,"passed_time":0.07699352571,"remaining_time":0.01690101784},
{"learn":[4.731700554],"iteration":82,"passed_time":0.07788568233,"remaining_time":0.01595248915},
{"learn":[4.723284153],"iteration":83,"passed_time":0.07878821087,"remaining_time":0.01500727826},
{"learn":[4.712232782],"iteration":84,"passed_time":0.07971070716,"remaining_time":0.01406659538},
{"learn":[4.703046867],"iteration":85,"passed_time":0.08061002,"remaining_time":0.0131225614},
{"learn":[4.698601855],"iteration":86,"passed_time":0.08158494908,"remaining_time":0.01219085446},
{"learn":[4.692429407],"iteration":87,"passed_time":0.08252876425,"remaining_time":0.0112539224},
{"learn":[4.675027364],"iteration":88,"passed_time":0.08346935118,"remaining_time":0.01031643666},
{"learn":[4.662368584],"iteration":89,"passed_time":0.08450170996,"remaining_time":0.009389078884},
{"learn":[4.646206172],"iteration":90,"passed_time":0.08544113867,"remaining_time":0.008450222506},
{"learn":[4.641245848],"iteration":91,"passed_time":0.08640136323,"remaining_time":0.00751316202},
{"learn":[4.633900435],"iteration":92,"passed_time":0.08735505974,"remaining_time":0.006575112023},
{"learn":[4.624738236],"iteration":93,"passed_time":0.08826207506,"remaining_time":0.005633749472},
{"learn":[4.612798287],"iteration":94,"passed_time":0.08913269186,"remaining_time":0.004691194309},
{"learn":[4.605222001],"iteration":95,"passed_time":0.09001239806,"remaining_time":0.003750516586},
{"learn":[4.601725912],"iteration":96,"passed_time":0.09099756884,"remaining_time":0.002814357799},
{"learn":[4.59722371],"iteration":97,"passed_time":0.09194033129,"remaining_time":0.001876333292},
{"learn":[4.580235665],"iteration":98,"passed_time":0.09279773671,"remaining_time":0.0009373508758},
{"learn":[4.57591791],"iteration":99,"passed_time":0.09368084303,"remaining_time":0}
]}